shapeprop/__init__.py
shapeprop/circle/__init__.py
shapeprop/circle/shape.py
shapeprop/triangle/__init__.py
shapeprop/triangle/shape.py
shapeprop/triangle/types.py
shapeprop-0.1.0.dist-info/LICENSE
shapeprop-0.1.0.dist-info/METADATA
shapeprop-0.1.0.dist-info/WHEEL
shapeprop-0.1.0.dist-info/top_level.txt
shapeprop-0.1.0.dist-info/RECORD
