Metadata-Version: 2.1
Name: shapeprop
Version: 0.1.0
Summary: A package on shape properties
Author-email: Ferdy <ferdymosca@gmail.com>
Project-URL: Homepage, https://github.com/fsmosca/shapeprop
Project-URL: Bug Tracker, https://github.com/fsmosca/shapeprop/issues
Classifier: Programming Language :: Python :: 3
Classifier: License :: OSI Approved :: MIT License
Classifier: Operating System :: OS Independent
Requires-Python: >=3.10
License-File: LICENSE
